alwaysdata_api/__init__.py
alwaysdata_api-0.9.4.dist-info/LICENSE.txt
alwaysdata_api-0.9.4.dist-info/METADATA
alwaysdata_api-0.9.4.dist-info/RECORD
alwaysdata_api-0.9.4.dist-info/WHEEL
alwaysdata_api-0.9.4.dist-info/top_level.txt
alwaysdata_api-0.9.4.dist-info/zip-safe
