Metadata-Version: 2.1
Name: alwaysdata-api
Version: 0.9.4
Summary: A dead simple Python interface to the Alwaysdata API.
Home-page: https://gitlab.com/wpk-/alwaysdata-api
Author: Paul Koppen
Author-email: alwaysdata-api@paulkoppen.com
License: MIT License
Keywords: api domain subdomain management web
Platform: UNKNOWN
Classifier: Development Status :: 4 - Beta
Classifier: Environment :: Web Environment
Classifier: Intended Audience :: Developers
Classifier: Intended Audience :: System Administrators
Classifier: License :: OSI Approved :: MIT License
Classifier: Programming Language :: Python
Classifier: Topic :: Software Development
Classifier: Topic :: Utilities
Requires-Dist: requests (>=2.1.0)
Requires-Dist: setuptools
